Metadata-Version: 1.0
Name: django-command-interface
Version: 0.5
Summary: A reusable Django app that allows to list manage.py commands and lauch them with one click
